gradpyent/__init__.py
gradpyent/colors.py
gradpyent/formats.py
gradpyent/gradient.py
gradpyent/rgb.py
gradpyent-0.9.5.dist-info/licenses/LICENSE
gradpyent-0.9.5.dist-info/METADATA
gradpyent-0.9.5.dist-info/WHEEL
gradpyent-0.9.5.dist-info/top_level.txt
gradpyent-0.9.5.dist-info/RECORD
