Metadata-Version: 2.4
Name: gradpyent
Version: 0.9.5
Summary: Create color gradients based on list-like input data
Author-email: Lyle Schlueter <lyle.schlueter@proton.me>
License: MIT
Project-URL: Homepage, https://github.com/lyle-schlueter/gradpyent
Project-URL: Documentation, https://lyle-schlueter.github.io/gradpyent/
Project-URL: Repository, https://github.com/lyle-schlueter/gradpyent
Project-URL: Issues, https://github.com/lyle-schlueter/gradpyent/issues
Keywords: color,gradient,palette,rgb,visualization
Classifier: Programming Language :: Python :: 3
Classifier: License :: OSI Approved :: MIT License
Classifier: Operating System :: OS Independent
Requires-Python: >=3.10
License-File: LICENSE
Provides-Extra: dev
Requires-Dist: pytest; extra == "dev"
Requires-Dist: pytest-cov; extra == "dev"
Requires-Dist: pytest-mock; extra == "dev"
Requires-Dist: ruff; extra == "dev"
Provides-Extra: docs
Requires-Dist: myst_parser; extra == "docs"
Requires-Dist: sphinx; extra == "docs"
Requires-Dist: sphinx-rtd-theme; extra == "docs"
Dynamic: license-file
